{
  "annotations": {
    "list": [
      {
        "builtIn": 1,
        "datasource": {
          "type": "grafana",
          "uid": "-- Grafana --"
        },
        "enable": true,
        "hide": true,
        "iconColor": "rgba(0, 211, 255, 1)",
        "name": "Annotations & Alerts",
        "type": "dashboard"
      }
    ]
  },
  "description": "This dashboard visualizes the propagation delay of anomalies as they move through the processing stages (P1 to P6). The anomaly counts (ae\\_anomalies\\_in\\_batch) for downstream stages are plotted using a $\\text{PromQL offset}$ to account for the expected 5-minute batch lag between stages. When an anomaly truly propagates, the peaks for all relevant stages will align vertically on the graph, allowing for easy verification of the system's pipeline flow.",
  "editable": true,
  "fiscalYearStartMonth": 0,
  "graphTooltip": 0,
  "id": 11,
  "links": [],
  "panels": [
    {
      "datasource": {
        "type": "prometheus",
        "uid": "PBFA97CFB590B2093"
      },
      "description": "Each line on this graph represents the anomaly count for a single stage. The time series are offset backward (e.g., P3 is offset -10m) to visually align all stage events to the moment the P1 source event occurred.",
      "fieldConfig": {
        "defaults": {
          "color": {
            "mode": "palette-classic"
          },
          "custom": {
            "axisBorderShow": false,
            "axisCenteredZero": false,
            "axisColorMode": "text",
            "axisLabel": "",
            "axisPlacement": "auto",
            "barAlignment": 0,
            "barWidthFactor": 0.6,
            "drawStyle": "line",
            "fillOpacity": 0,
            "gradientMode": "none",
            "hideFrom": {
              "legend": false,
              "tooltip": false,
              "viz": false
            },
            "insertNulls": false,
            "lineInterpolation": "linear",
            "lineWidth": 1,
            "pointSize": 5,
            "scaleDistribution": {
              "type": "linear"
            },
            "showPoints": "always",
            "showValues": false,
            "spanNulls": true,
            "stacking": {
              "group": "A",
              "mode": "none"
            },
            "thresholdsStyle": {
              "mode": "off"
            }
          },
          "mappings": [],
          "thresholds": {
            "mode": "absolute",
            "steps": [
              {
                "color": "green",
                "value": 0
              },
              {
                "color": "red",
                "value": 80
              }
            ]
          }
        },
        "overrides": []
      },
      "gridPos": {
        "h": 15,
        "w": 24,
        "x": 0,
        "y": 0
      },
      "id": 1,
      "options": {
        "legend": {
          "calcs": [],
          "displayMode": "list",
          "placement": "bottom",
          "showLegend": true
        },
        "tooltip": {
          "hideZeros": false,
          "mode": "single",
          "sort": "asc"
        }
      },
      "pluginVersion": "12.2.1",
      "targets": [
        {
          "datasource": {
            "type": "prometheus",
            "uid": "PBFA97CFB590B2093"
          },
          "editorMode": "builder",
          "expr": "ae_anomalies_in_batch{stage=\"P1\"}",
          "instant": false,
          "legendFormat": "P1 (Source)",
          "range": true,
          "refId": "A"
        },
        {
          "datasource": {
            "type": "prometheus",
            "uid": "PBFA97CFB590B2093"
          },
          "editorMode": "code",
          "expr": "ae_anomalies_in_batch{stage=\"P2\"} offset 5m",
          "hide": false,
          "instant": false,
          "legendFormat": "P2 (Lag -5m)",
          "range": true,
          "refId": "B"
        },
        {
          "datasource": {
            "type": "prometheus",
            "uid": "PBFA97CFB590B2093"
          },
          "editorMode": "code",
          "expr": "ae_anomalies_in_batch{stage=\"P3\"} offset 10m",
          "hide": false,
          "instant": false,
          "legendFormat": "P3 (Lag -10m)",
          "range": true,
          "refId": "C"
        },
        {
          "datasource": {
            "type": "prometheus",
            "uid": "PBFA97CFB590B2093"
          },
          "editorMode": "code",
          "expr": "ae_anomalies_in_batch{stage=\"P4\"} offset 15m",
          "hide": false,
          "instant": false,
          "legendFormat": "P4 (Lag -15m)",
          "range": true,
          "refId": "D"
        },
        {
          "datasource": {
            "type": "prometheus",
            "uid": "PBFA97CFB590B2093"
          },
          "editorMode": "code",
          "expr": "ae_anomalies_in_batch{stage=\"P5\"} offset 20m",
          "hide": false,
          "instant": false,
          "legendFormat": "P5 (Lag -20m)",
          "range": true,
          "refId": "E"
        },
        {
          "datasource": {
            "type": "prometheus",
            "uid": "PBFA97CFB590B2093"
          },
          "editorMode": "code",
          "expr": "ae_anomalies_in_batch{stage=\"P6\"} offset 25m",
          "hide": false,
          "instant": false,
          "legendFormat": "P6 (Lag -25m)",
          "range": true,
          "refId": "F"
        }
      ],
      "title": "Time-Aligned Anomaly Counts",
      "type": "timeseries"
    }
  ],
  "preload": false,
  "refresh": "5s",
  "schemaVersion": 42,
  "tags": [
    "anomaly"
  ],
  "templating": {
    "list": []
  },
  "time": {
    "from": "now-30m",
    "to": "now"
  },
  "timepicker": {},
  "timezone": "browser",
  "title": "Anomaly Propagation & Lag Analysis",
  "uid": "ad2vpz2",
  "version": 1
}